colortransfer/__init__.py
imgaug_extension/__init__.py
imgaug_extension/extension.py
imgaug_extension-1.0.5.dist-info/DESCRIPTION.rst
imgaug_extension-1.0.5.dist-info/METADATA
imgaug_extension-1.0.5.dist-info/RECORD
imgaug_extension-1.0.5.dist-info/WHEEL
imgaug_extension-1.0.5.dist-info/metadata.json
imgaug_extension-1.0.5.dist-info/top_level.txt
objectinsertion/__init__.py
src/__init__.py
src/imgaug_extension.py
