Metadata-Version: 2.0
Name: imgaug-extension
Version: 1.0.5
Summary: Extension package for imgaug
Home-page: https://github.com/cadenai/imgaug_extension
Author: caden.ai
Author-email: info@caden.ai
License: UNKNOWN
Download-URL: https://github.com/cadenai/imgaug_extension/archive/1.0.tar.gz
Platform: UNKNOWN
Requires-Dist: imgaug
Requires-Dist: numpy
Requires-Dist: scikit-image (>=0.13.1)
